django_axios/__init__.py
django_axios/apps.py
django_axios/settings.py
django_axios/socket.py
django_axios-0.1.0.dist-info/LICENSE
django_axios-0.1.0.dist-info/METADATA
django_axios-0.1.0.dist-info/WHEEL
django_axios-0.1.0.dist-info/RECORD
