Metadata-Version: 2.1
Name: django-axios
Version: 0.1.0
Summary: emit events from django views or django database changes via python-socketio
License: MIT
Author: Oguntunde Caleb
Author-email: usegong@gmail.com
Requires-Python: >=3.11,<4.0
Classifier: License :: OSI Approved :: MIT License
Classifier: Programming Language :: Python :: 3
Classifier: Programming Language :: Python :: 3.11
